{
	"css/bundle_shared.css": {
		"type": "css",
		"files": [
			"css/boilerplate.css",
			"css/layout.css",
			"css/style.css",
			"css/style_modal.css",
			"css/boilerplate_after.css",
			"css/rainbow.css",
			"css/tipsy.css",
			"css/content.css"
		]
	},
	"js/bundle_shared.js": {
		"type": "js",
		"files": [
			"js/json2.js",
			"js/cookie.js",
			"js/app_rsrc.js",
			"js/app_modal.js",
			"js/app.js",
			"js/mustache.js",
			"js/jquery.tipsy.js",
			"js/site.js"
		]
	},
	"css/bundle_www.css": {
		"type": "css",
		"files": [
			"css/openid.css",
			"css/404.css",
			"css/blog.css",
			"css/page.css",
			"css/hssdoc.css",
			"css/downloads.css",
			"css/manifesto.css",
			"css/calendar.css",
			"css/home.css",
			"css/auth.css",
			"css/account.css",
			"css/get_involved.css"
		]
	},
	"js/bundle_www.js": {
		"type": "js",
		"files": [
			"js/openid-jquery.js",
			"js/openid-en.js",
			"js/auth.js",
			"js/home.js",
			"js/get_involved.js",
			"js/hssdoc.js"
		]
	},
	"js/downloads.js": {
		"type": "js",
		"files": [
			"js/downloads.js"
		]
	},
	"css/bundle_wiki.css": {
		"type": "css",
		"files": [
			"css/404.css",
			"css/wiki/page.css",
			"css/wiki/index.css"
		]
	},
	"js/bundle_wiki.js": {
		"type": "js",
		"files": [
			"js/app_auth.js",
			"js/openid-jquery.js",
			"js/openid-en.js",
			"js/wiki/mixed_login.js"
		]
	},
	"js/bundle_rainbow.js": {
		"type": "js",
		"files": [
			"js/rainbow/rainbow.js",
			"js/rainbow/css.js",
			"js/rainbow/hss.js",
			"js/rainbow/xml.js"
		]
	}
}
